<?xml version="1.0" encoding="UTF-8"?>
<!DOCTYPE suite SYSTEM "https://testng.org/testng-1.0.dtd">
<suite name="Suite">
  <test thread-count="5" name="Test">
  <!-- way to create a comment in xml file-->
  <!-- //Group Execution code
	//select all classes from demo 1 to 5 
	//right click -> run with -> convert to testNG suite
	//Name it Group.xml in the place of testNG.xml 
	//finish it
	//your Group.xml file is created
	
	<groups>
	<run>
	<include name="smoke"></include>
	<exclude name="reg></exclude>
	</run>
	</groups>
	
	//open the file and run it -->
  <groups>
  <run>
  <include name="smoke"></include>
  <!-- <include name="reg"></include>-->
  <exclude name="reg"></exclude>
  </run>
  </groups>
  
    <classes>
      <class name="PracticeDay9TestNG.Demo1"/>
      <class name="PracticeDay9TestNG.Demo2"/>
      <class name="PracticeDay9TestNG.Demo3"/>
      <class name="PracticeDay9TestNG.Demo4"/>
      <class name="PracticeDay9TestNG.Demo5"/>
    </classes>
  </test> <!-- Test -->
</suite> <!-- Suite -->